AUTHORS.txt
LICENSE.txt
MANIFEST.in
README.rst
setup.cfg
setup.py
django_fack.egg-info/PKG-INFO
django_fack.egg-info/SOURCES.txt
django_fack.egg-info/dependency_links.txt
django_fack.egg-info/not-zip-safe
django_fack.egg-info/requires.txt
django_fack.egg-info/top_level.txt
docs/Makefile
docs/conf.py
docs/customization.rst
docs/getting-started.rst
docs/index.rst
docs/make.bat
example/__init__.py
example/manage.py
example/settings.py
example/urls.py
example/templates/home.html
fack/__init__.py
fack/_testrunner.py
fack/admin.py
fack/forms.py
fack/managers.py
fack/models.py
fack/urls.py
fack/views.py
fack/fixtures/faq_test_data.json
fack/templates/faq/base.html
fack/templates/faq/question_detail.html
fack/templates/faq/submit_question.html
fack/templates/faq/submit_thanks.html
fack/templates/faq/topic_detail.html
fack/templates/faq/topic_list.html
fack/templatetags/__init__.py
fack/templatetags/faqtags.py
fack/tests/__init__.py
fack/tests/test_admin.py
fack/tests/test_models.py
fack/tests/test_templatetags.py
fack/tests/test_views.py