Metadata-Version: 1.0
Name: django-fack
Version: 1.1
Summary: A simple FAQ application for Django sites.
Home-page: http://django-fack.rtfd.org/
Author: Kevin Fricovsky
Author-email: kfricovsky@gmail.com
License: BSD
Platform: UNKNOWN
Classifier: Development Status :: 3 - Alpha
Classifier: Environment :: Web Environment
Classifier: Intended Audience :: Developers
Classifier: License :: OSI Approved :: BSD License
Classifier: Operating System :: OS Independent
Classifier: Programming Language :: Python
Classifier: Framework :: Django
